dlg_paletteGen/__init__.py
dlg_paletteGen/__main__.py
dlg_paletteGen/classes.py
dlg_paletteGen/module_base.py
dlg_paletteGen/settings.py
dlg_paletteGen/source_base.py
dlg_paletteGen/support_functions.py
dlg_palettegen-0.6.7.dist-info/licenses/LICENSE
dlg_palettegen-0.6.7.dist-info/METADATA
dlg_palettegen-0.6.7.dist-info/WHEEL
dlg_palettegen-0.6.7.dist-info/entry_points.txt
dlg_palettegen-0.6.7.dist-info/top_level.txt
dlg_palettegen-0.6.7.dist-info/RECORD
