Metadata-Version: 2.4
Name: dlg_paletteGen
Version: 0.6.7
Summary: DALiuGE palette generator tool
Home-page: https://github.com/ICRAR/dlg_paletteGen/
Author: ICRAR
License-File: LICENSE
Requires-Dist: python-benedict
Requires-Dist: numpy
Requires-Dist: blockdag
Requires-Dist: docstring-parser
Requires-Dist: numpy
Requires-Dist: google-genai
Provides-Extra: test
Requires-Dist: pytest; extra == "test"
Requires-Dist: pytest-datadir; extra == "test"
Requires-Dist: coverage; extra == "test"
Requires-Dist: flake8; extra == "test"
Requires-Dist: black; extra == "test"
Requires-Dist: isort; extra == "test"
Requires-Dist: pytest-cov; extra == "test"
Requires-Dist: codecov; extra == "test"
Requires-Dist: mypy; extra == "test"
Requires-Dist: gitchangelog; extra == "test"
Requires-Dist: mkdocs; extra == "test"
Requires-Dist: types-setuptools; extra == "test"
Requires-Dist: python-benedict; extra == "test"
Dynamic: author
Dynamic: description
Dynamic: description-content-type
Dynamic: home-page
Dynamic: license-file
Dynamic: provides-extra
Dynamic: requires-dist
Dynamic: summary
